{
  "children": [
    {
      "id": "/page/0/Page/5",
      "block_type": "Page",
      "html": "<content-ref src='/page/0/PageHeader/0'></content-ref><content-ref src='/page/0/PageHeader/1'></content-ref><content-ref src='/page/0/Table/2'></content-ref><content-ref src='/page/0/PageHeader/3'></content-ref><content-ref src='/page/0/Table/4'></content-ref><content-ref src='/page/0/PageFooter/5'></content-ref>",
      "polygon": [
        [
          0,
          0
        ],
        [
          2246,
          0
        ],
        [
          2246,
          1587
        ],
        [
          0,
          1587
        ]
      ],
      "bbox": [
        0,
        0,
        2246,
        1587
      ],
      "children": [
        {
          "id": "/page/0/PageHeader/0",
          "block_type": "PageHeader",
          "html": "Fol. 12",
          "polygon": [
            [
              303,
              147
            ],
            [
              375,
              147
            ],
            [
              375,
              176
            ],
            [
              303,
              176
            ]
          ],
          "bbox": [
            303,
            147,
            375,
            176
          ],
          "children": null,
          "section_hierarchy": {},
          "images": {},
          "page": 0
        },
        {
          "id": "/page/0/PageHeader/1",
          "block_type": "PageHeader",
          "html": "Trauungs-",
          "polygon": [
            [
              866,
              133
            ],
            [
              1060,
              133
            ],
            [
              1060,
              172
            ],
            [
              866,
              172
            ]
          ],
          "bbox": [
            866,
            133,
            1060,
            172
          ],
          "children": null,
          "section_hierarchy": {},
          "images": {},
          "page": 0
        },
        {
          "id": "/page/0/Table/2",
          "block_type": "Table",
          "html": "<table><thead><tr><th colspan=\"4\">Jahr 1909</th><th colspan=\"6\">Bräutigam<br/>(Nach jeder Trauung sind die Trauungsakten, bei Minderjährigen)</th></tr><tr><th rowspan=\"2\">Monat</th><th rowspan=\"2\">Tag</th><th rowspan=\"2\">Ortschaft</th><th rowspan=\"2\">Haus-Nr.</th><th rowspan=\"2\">Name</th><th colspan=\"2\">Religion</th><th rowspan=\"2\">Altersjahre</th><th rowspan=\"2\">Unverehelicht</th><th rowspan=\"2\">Witwer</th></tr><tr><th>katholisch</th><th>protestantisch</th></tr></thead><tbody><tr><td>3. Februar<br/>/ vierzehnten /</td><td>14</td><td>Aich<br/>/ Rapplwirt /</td><td>84</td><td>Starmann Blasius, lediger<br/>Laborant in Freibach, aus Oberam-<br/>lach vulgo Aishlerhütte Pfarre Amlach<br/>bei Spittal an der Drau den 12.<br/>September 1879 gebürtig, ein natür-<br/>licher Sohn der schon seligen röm.<br/>katholischen Wirthschafterin in<br/>Oberamlach Starmann Agnes, nach<br/>Medvode bei Laibach in Krain<br/>zuständig, hier wohnhaft, römisch<br/>katholisch.</td><td>1</td><td></td><td>29<math>\\frac{1}{2}</math></td><td>1</td><td></td></tr><tr><td colspan=\"10\">Dieses Brautpaar wurde am 2. und 14. Februar 1909 in der Pfarrkirche Althofen vor<br/>schriftmässig verkündet, und da kein gesetzliches Ehehindernis oder Verbot entdeckt worden<br/>ist, am vierzehnten /: 14. Februar 1909 in der Pfarrkirche St. Thomas Cant in<br/>Althofen nach dem nachmittägigen Gottesdienste kirchlich eingesegnet vom Pfarrer<br/>Josef Adalbert Rubizga.</td></tr><tr><td>4. Mai<br/>/ zweiten /</td><td>2</td><td>Althofen<br/>/ Untere Markt /</td><td>48</td><td>Knafl Johann, verwitweter<br/>Realitätenbesitzer und Sägefabrikant<br/>hier, seit 13. Mai 1908 Witwer, ein<br/>ehelicher Sohn des schon verstorbenen<br/>Besitzers der Hannhübe in Jochatoch<br/>Josef Knafl und seiner ebenfalls<br/>verstorbenen Ehefrau Maria gebore-<br/>nen Kasser, beide römisch katho-<br/>lisch, aus Jochatoch vulgo Hannhübe<br/>Haus N 3, Pfarre Meiselding den<br/>17. November 1860 gebürtig und<br/>nach Rabing Bezirk St. Veit a.<br/>d. Glan zuständig, römisch ka-<br/>tholisch.</td><td>1</td><td></td><td>48</td><td></td><td>1</td></tr><tr><td colspan=\"10\" style=\"text-align: left;\">+ 19. 7. 1941<br/>St. Althofen 11/1941</td></tr><tr><td colspan=\"10\">Dieses Brautpaar wurde am 18. und 25. April und am 2. Mai 1909 in der Pfarrkirche<br/>Althofen vorschriftsmässig von der Kanzel verlautbart, und da kein gesetzliches Ehe-<br/>hindernis oder Verbot entdeckt worden ist, am zweiten /: 2. Mai 1909 / nein /<br/>in der Wallfahrtskirche zu Maria Hilfschert nach dem feierlichen Segen kirchlich<br/>eingesegnet vom Ortspfarrer Josef Adalbert Rubizga.</td></tr></tbody></table>",
          "polygon": [
            [
              298,
              182
            ],
            [
              1060,
              182
            ],
            [
              1060,
              1439
            ],
            [
              298,
              1439
            ]
          ],
          "bbox": [
            298,
            182,
            1060,
            1439
          ],
          "children": [],
          "section_hierarchy": {},
          "images": null,
          "page": 0
        },
        {
          "id": "/page/0/PageHeader/3",
          "block_type": "PageHeader",
          "html": "Buch.",
          "polygon": [
            [
              1170,
              131
            ],
            [
              1262,
              131
            ],
            [
              1262,
              168
            ],
            [
              1170,
              168
            ]
          ],
          "bbox": [
            1170,
            131,
            1262,
            168
          ],
          "children": null,
          "section_hierarchy": {},
          "images": {},
          "page": 0
        },
        {
          "id": "/page/0/Table/4",
          "block_type": "Table",
          "html": "<table><thead><tr><th colspan=\"6\">Braut</th><th colspan=\"2\">Beistände</th></tr><tr><td colspan=\"6\" style=\"text-align: center;\">(auch die erhaltene gesetzliche Einwilligung angemerkt.)</td><td colspan=\"2\"></td></tr><tr><th rowspan=\"2\">Name</th><th colspan=\"2\">Religion</th><th rowspan=\"2\">Altersjahre</th><th rowspan=\"2\">Unverehelicht</th><th rowspan=\"2\">Witwe</th><th rowspan=\"2\">Namen</th><th rowspan=\"2\">Stand</th></tr><tr><th>katholisch</th><th>protestantisch</th></tr></thead><tbody><tr><td rowspan=\"3\">Öhner Apolonia, ledige Magd<br/>beim vulgo Rapplwirt in Aich<br/>Haus N 84, eine aussercheliche<br/>Tochter der noch lebenden röm.<br/>katholischen Magd in St. Georg<br/>unter Straßburg Theresia Ofner,<br/>aus Lieding im Gurkthale<br/>am siebenten Februar 1881<br/>gebürtig, hier wohnhaft, röm.<br/>Katholisch.</td><td>1</td><td></td><td>28</td><td>1</td><td></td><td>Johann Starmann Bruder<br/>d. e. Starmann</td><td>in Freibach</td></tr><tr><td colspan=\"5\"></td><td>Karl Krumper</td><td>Holzarbeiter</td></tr><tr><td colspan=\"5\"></td><td>Bartholomäus Mühmayer</td><td>in Jochsdorf.</td></tr><tr><td colspan=\"8\"><p style=\"text-align: center;\">Eheakten:</p>1) Taufschein der Braut ddo 29. Mai 1908 Z: 154<br/>2) \" \" des Bräutigams ddo 4. Februar 1909 Z: 51.<br/>3) Eheaufnahme ddo 24. Jänner 1909 Z: 71.<br/>4) Verkündzettel des hiesigen Pfarramtes.</td></tr><tr><td colspan=\"8\">gestorben am<br/>12. 1. 1966 in<br/>Klagenfurt, S 82/66</td></tr><tr><td colspan=\"8\">Trauungschein am 4. Februar 1914 Z. 533.</td></tr><tr><td rowspan=\"2\">Franziska Schöffmann, ledige<br/>Wirthschafterin beim Bräutigam,<br/>eine eheliche Tochter des Franz<br/>Schöffmann vulgo Hannibauer<br/>in Straganz, Pfarre Meiselding<br/>und seiner Ehefrau Johanna<br/>geborenen Stainer, aus<br/>Straganz vulgo Hannibauer Haus<br/>N 6, Pfarre Meiselding den<br/>11. Oktober 1878 gebürtig,<br/>seit Juli 1908 hier wohnhaft,<br/>römisch katholisch.</td><td>1</td><td></td><td>31<math>\\frac{1}{2}</math></td><td>1</td><td></td><td>Rudolf Koppitsch</td><td>Besitzer<br/>Straganz.</td></tr><tr><td colspan=\"5\"></td><td>Donat Schöffmann</td><td>Landwirthssohn<br/>in Möringberg.</td></tr><tr><td colspan=\"8\">+ 1. 4. 1951 in Althofen, 40.</td></tr><tr><td colspan=\"8\"><p style=\"text-align: center;\">Ehedocumente:</p>1) Taufschein des Bräutigams ddo 12. April 1909<br/>2) \" \" der Braut ddo 12. April 1909.<br/>3) Eheaufnahme ddo 17. April 1909 Z: 191.<br/>4) Verkündzettel des hiesigen Pfarramtes.</td></tr><tr><td colspan=\"8\" style=\"text-align: center;\">Josef Adalbert Rubizga</td></tr></tbody></table>",
          "polygon": [
            [
              1170,
              198
            ],
            [
              1924,
              198
            ],
            [
              1924,
              1439
            ],
            [
              1170,
              1439
            ]
          ],
          "bbox": [
            1170,
            198,
            1924,
            1439
          ],
          "children": [],
          "section_hierarchy": {},
          "images": null,
          "page": 0
        },
        {
          "id": "/page/0/PageFooter/5",
          "block_type": "PageFooter",
          "html": "",
          "polygon": [
            [
              1924,
              1060
            ],
            [
              1936,
              1060
            ],
            [
              1936,
              1393
            ],
            [
              1924,
              1393
            ]
          ],
          "bbox": [
            1924,
            1060,
            1936,
            1393
          ],
          "children": null,
          "section_hierarchy": {},
          "images": {},
          "page": 0
        }
      ],
      "section_hierarchy": {},
      "images": null,
      "page": 0
    }
  ],
  "block_type": "Document"
}